<?xml version="1.0" encoding="UTF-8"?>
<site>
	<description>To install these features, point Eclipse at this site.</description>
	<!-- Mobicents EclipSLEE Nightly Build Update Site -->
	<category-def name="Mobicents EclipSLEE Nightly Build Update Site" label="Mobicents EclipSLEE Nightly Build Update Site">
		<description>Mobicents EclipSLEE Nightly Build Update Site: contains all features in this build.</description>
	</category-def>
	<feature url="features/org.mobicents.eclipslee_0.0.0.jar" id="org.mobicents.eclipslee" version="0.0.0">
		<category name="Mobicents EclipSLEE Nightly Build Update Site"/>
	</feature>
</site>
